{"cameraMode":{"drawMode":0,"name":"Shaded","section":"Shading Mode"},"sceneLighting":false,"audioPlay":false,"sceneViewState":{"showFog":true,"showMaterialUpdate":false,"showSkybox":false,"showFlares":true,"showImageEffects":true,"showParticleSystems":true},"in2DMode":false,"pivot":{"x":0.10625505447387696,"y":1.7881393432617188e-7,"z":-0.04527932405471802},"rotation":{"x":0.058158669620752338,"y":-0.8060194849967957,"z":0.08029928803443909,"w":0.5835675597190857},"size":1.37621009349823,"orthographic":false}